Metadata-Version: 1.1
Name: collective.local.sentmail
Version: 1.0.1
Summary: Keep history of emails sent by collective.local.sendto
Home-page: http://pypi.python.org/pypi/collective.local.sentmail
Author: Cédric Messiant
Author-email: cedricmessiant@ecreall.com
License: GPL
Keywords: email,sendto,dexterity
Platform: UNKNOWN
Classifier: Environment :: Web Environment
Classifier: Framework :: Plone
Classifier: Framework :: Plone :: 4.3
Classifier: Programming Language :: Python
Classifier: Programming Language :: Python :: 2.7
